{
  "fluentMethods": true,
  "clientRootFolder": "",
  "relationships": [],
  "fields": [
    {
      "fieldName": "code",
      "fieldType": "String",
      "fieldValidateRules": ["unique"]
    },
    {
      "fieldName": "libelle",
      "fieldType": "String"
    }
  ],
  "changelogDate": "20200618161239",
  "dto": "no",
  "searchEngine": false,
  "service": "serviceClass",
  "entityTableName": "periode",
  "databaseType": "sql",
  "readOnly": false,
  "jpaMetamodelFiltering": false,
  "pagination": "pagination"
}
